pytorch_pretrained_biggan/__init__.py
pytorch_pretrained_biggan/config.py
pytorch_pretrained_biggan/convert_tf_to_pytorch.py
pytorch_pretrained_biggan/file_utils.py
pytorch_pretrained_biggan/model.py
pytorch_pretrained_biggan/utils.py
pytorch_pretrained_biggan-0.1.1.dist-info/LICENSE
pytorch_pretrained_biggan-0.1.1.dist-info/METADATA
pytorch_pretrained_biggan-0.1.1.dist-info/WHEEL
pytorch_pretrained_biggan-0.1.1.dist-info/entry_points.txt
pytorch_pretrained_biggan-0.1.1.dist-info/top_level.txt
pytorch_pretrained_biggan-0.1.1.dist-info/RECORD
