Metadata-Version: 2.1
Name: pytorch-pretrained-biggan
Version: 0.1.1
Summary: PyTorch version of DeepMind's BigGAN model with pre-trained models
Home-page: https://github.com/huggingface/pytorch-pretrained-BigGAN
Author: Thomas Wolf
Author-email: thomas@huggingface.co
License: Apache
Keywords: BIGGAN GAN deep learning google deepmind
Platform: UNKNOWN
Classifier: Intended Audience :: Science/Research
Classifier: License :: OSI Approved :: Apache Software License
Classifier: Programming Language :: Python :: 3
Classifier: Topic :: Scientific/Engineering :: Artificial Intelligence
Requires-Dist: torch (>=0.4.1)
Requires-Dist: numpy
Requires-Dist: boto3
Requires-Dist: requests
Requires-Dist: tqdm
